yellowduck/__init__.py
yellowduck/package.py
yellowduck/service.py
seatbelt-0.1.0.dist-info/METADATA
seatbelt-0.1.0.dist-info/WHEEL
seatbelt-0.1.0.dist-info/top_level.txt
seatbelt-0.1.0.dist-info/RECORD
