Metadata-Version: 2.1
Name: seatbelt
Version: 0.1.0
Summary: A Seatbelt package
Home-page: https://github.com/yellowduckcompany/packages
Author: The Yellow Duck Company
Author-email: hello@yellowduckcompany.com
Classifier: Programming Language :: Python :: 3
Classifier: License :: OSI Approved :: MIT License
Classifier: Operating System :: OS Independent
Requires-Python: >=3.8
